<?xml version="1.0" encoding="UTF-8"?>

<!DOCTYPE mapper PUBLIC "-//mybatis.org//DTD Mapper 3.0//EN" "http://mybatis.org/dtd/mybatis-3-mapper.dtd">

<mapper namespace="com.ysh.CoS.mapper.freeBoardMapper">

	<select id="list" parameterType="hashmap" resultType="com.ysh.CoS.dto.boardDTO">
	
		select * from (select b.*, m.name, ROW_NUMBER() OVER(order by bSeq desc) as 'bNo' from tblBoard b inner join tblMember m on b.mseq = m.mseq) r where bNo between ${begin} and ${end}
	
	</select>
	
	<select id="listSingleSearch" parameterType="hashmap" resultType="com.ysh.CoS.dto.boardDTO">
	
		select * from (select b.*, m.name, ROW_NUMBER() OVER(order by bSeq desc) as 'bNo' from tblBoard b inner join tblMember m on b.mseq = m.mseq where ${search} like '%${word}%') r where bNo between ${begin} and ${end}
	
	</select>
	
	<select id="listAllSearch" parameterType="hashmap" resultType="com.ysh.CoS.dto.boardDTO">
	
		select * from (select b.*, m.name, ROW_NUMBER() OVER(order by bSeq desc) as 'bNo' from tblBoard b inner join tblMember m on b.mseq = m.mseq where bTitle like '%${word}%' || bContent like '%${word}%' || name like '%${word}%') r where bNo between ${begin} and ${end}
	
	</select>
	
	<select id="getTotalCount" parameterType="hashmap" resultType="Integer">
	
		select count(*) from tblBoard
	
	</select>
	
	<select id="getSingleSearchCount" parameterType="hashmap" resultType="Integer">
	
		select count(*) from tblBoard b inner join tblMember m on b.mseq = m.mseq where ${search} like '%${word}%'
	
	</select>
	
	<select id="getAllSearchCount" parameterType="hashmap" resultType="Integer">
	
		select count(*) from tblBoard b inner join tblMember m on b.mseq = m.mseq where bTitle like '%${word}%' || bContent like '%${word}%' || name like '%${word}%'
	
	</select>
	
</mapper>